gllm_memory.cpython-312-x86_64-linux-gnu.so
gllm_memory.pyi
gllm_memory/__init__.pyi
gllm_memory/enums.pyi
gllm_memory/memory_manager.pyi
gllm_memory/schema.pyi
gllm_memory/builder/__init__.pyi
gllm_memory/builder/build_memory_client.pyi
gllm_memory/chat_history_manager/__init__.pyi
gllm_memory/chat_history_manager/chat_history_manager.pyi
gllm_memory/chat_history_manager/chat_history_processor/__init__.pyi
gllm_memory/chat_history_manager/chat_history_processor/chat_history_processor.pyi
gllm_memory/chat_history_manager/chat_history_processor/lm_based_chat_history_processor.pyi
gllm_memory/chat_history_manager/chat_history_processor/similarity_based_chat_history_processor.pyi
gllm_memory/chat_history_manager/schema/__init__.pyi
gllm_memory/chat_history_manager/schema/schema.pyi
gllm_memory/clients/__init__.pyi
gllm_memory/clients/constants.pyi
gllm_memory/clients/memory_client.pyi
gllm_memory/clients/utils.pyi
gllm_memory/clients/mem0/__init__.pyi
gllm_memory/clients/mem0/mem0_add_important_policy.pyi
gllm_memory/clients/mem0/mem0_chunk_creator.pyi
gllm_memory/clients/mem0/mem0_client.pyi
gllm_memory/clients/mem0/mem0_filter_builder.pyi
gllm_memory/clients/mem0/mem0_filter_enhancer.pyi
gllm_memory/clients/mem0/mem0_filter_strategy.pyi
gllm_memory/clients/mem0/mem0_message_mapper.pyi
gllm_memory/clients/mem0/mem0_response_processor.pyi
gllm_memory/clients/mem0/mem0_self_hosted_client.pyi
gllm_memory.build/.gitignore
gllm_memory_binary-0.1.8.dist-info/METADATA
gllm_memory_binary-0.1.8.dist-info/WHEEL
gllm_memory_binary-0.1.8.dist-info/top_level.txt
gllm_memory_binary-0.1.8.dist-info/RECORD
