Metadata-Version: 2.2
Name: gllm-memory-binary
Version: 0.1.8
Summary: A flexible memory system for Gen AI applications
Author-email: Budi Kurniawan <budi.kurniawan1@gdplabs.id>
Requires-Python: <3.14,>=3.11
Requires-Dist: gllm-core-binary<0.4.0,>=0.3.0
Requires-Dist: gllm-inference-binary<0.6.0,>=0.5.0
Requires-Dist: gllm-datastore-binary<0.6.0,>=0.5.0
Requires-Dist: pydantic<3.0.0,>=2.11.4
Requires-Dist: scipy<2.0.0,>=1.15.1
Requires-Dist: python-dotenv<2.0.0,>=1.0.0
Requires-Dist: python-json-logger<4.0.0,>=3.3.0
Requires-Dist: pyyaml<7.0.0,>=6.0
Requires-Dist: typing-extensions<5.0.0,>=4.8.0
Requires-Dist: langchain-core<1.0.0,>=0.3.0
Requires-Dist: langchain-community<1.0.0,>=0.3.0
Requires-Dist: filetype<2.0.0,>=1.2.0
Requires-Dist: python-magic<0.5.0,>=0.4.27; sys_platform != "win32"
Requires-Dist: python-magic-bin<0.5.0,>=0.4.14; sys_platform == "win32"
Provides-Extra: dev
Requires-Dist: coverage<8.0.0,>=7.4.4; extra == "dev"
Requires-Dist: httpx<1.0.0,>=0.28.0; extra == "dev"
Requires-Dist: mypy<2.0.0,>=1.15.0; extra == "dev"
Requires-Dist: pre-commit<4.0.0,>=3.7.0; extra == "dev"
Requires-Dist: pytest<9.0.0,>=8.1.1; extra == "dev"
Requires-Dist: pytest-asyncio<1.0.0,>=0.23.6; extra == "dev"
Requires-Dist: pytest-cov<6.0.0,>=5.0.0; extra == "dev"
Requires-Dist: ruff<1.0.0,>=0.6.7; extra == "dev"
Provides-Extra: mem0ai
Requires-Dist: mem0ai<2.0.0,>=0.1.117; extra == "mem0ai"
